ib_trading_calendars/__init__.py
ib_trading_calendars/_version.py
ib_trading_calendars/calendar_utils.py
ib_trading_calendars/exchange_calendar_aeb.py
ib_trading_calendars/exchange_calendar_asx.py
ib_trading_calendars/exchange_calendar_bm.py
ib_trading_calendars/exchange_calendar_bux.py
ib_trading_calendars/exchange_calendar_bvl.py
ib_trading_calendars/exchange_calendar_bvme.py
ib_trading_calendars/exchange_calendar_cboe.py
ib_trading_calendars/exchange_calendar_ebs.py
ib_trading_calendars/exchange_calendar_enextbe.py
ib_trading_calendars/exchange_calendar_fwb.py
ib_trading_calendars/exchange_calendar_globex.py
ib_trading_calendars/exchange_calendar_iceus.py
ib_trading_calendars/exchange_calendar_kse.py
ib_trading_calendars/exchange_calendar_lse.py
ib_trading_calendars/exchange_calendar_mexi.py
ib_trading_calendars/exchange_calendar_moex.py
ib_trading_calendars/exchange_calendar_nyse.py
ib_trading_calendars/exchange_calendar_ose.py
ib_trading_calendars/exchange_calendar_sbf.py
ib_trading_calendars/exchange_calendar_sehk.py
ib_trading_calendars/exchange_calendar_sehkntl.py
ib_trading_calendars/exchange_calendar_sfb.py
ib_trading_calendars/exchange_calendar_sgx.py
ib_trading_calendars/exchange_calendar_tse.py
ib_trading_calendars/exchange_calendar_tsej.py
ib_trading_calendars/exchange_calendar_vse.py
ib_trading_calendars/exchange_calendar_wse.py
ib_trading_calendars/status.py
ib_trading_calendars-2.0.0.dist-info/LICENSE
ib_trading_calendars-2.0.0.dist-info/METADATA
ib_trading_calendars-2.0.0.dist-info/WHEEL
ib_trading_calendars-2.0.0.dist-info/entry_points.txt
ib_trading_calendars-2.0.0.dist-info/top_level.txt
ib_trading_calendars-2.0.0.dist-info/RECORD
